tf_decompose/__init__.py
tf_decompose/dtensor.py
tf_decompose/ktensor.py
tf_decompose/ttensor.py
tf_decompose/utils.py
tf_decompose-0.1.0.dist-info/METADATA
tf_decompose-0.1.0.dist-info/RECORD
tf_decompose-0.1.0.dist-info/WHEEL
tf_decompose-0.1.0.dist-info/top_level.txt
