Metadata-Version: 2.1
Name: tf-decompose
Version: 0.1.0
Summary: Tensor decomposition with TensorFlow
Home-page: https://github.com/chengscott/tf-decompose
Author: ebigelow, chengscott
Maintainer: chengscott
License: UNKNOWN
Platform: UNKNOWN
Requires-Dist: tensorflow
Requires-Dist: numpy
Requires-Dist: scipy
